{"p":0,"d":{},"t":1587139107.94385,"m":"ConcurrentEA","n":"Events","k":0,"c":"Events"}
{"k":0,"c":"Events","p":0,"d":{"start-at":"2020-04-17T17:57:50.945661+02:00","length":60,"generations":16,"population-size":512,"initial-populations":3,"threads":2},"t":1587139107.946407,"m":"ConcurrentEA","n":"Events"}
{"n":"Evolutionary","m":"ConcurrentEA","t":1587139107.950843,"i":1,"d":{},"p":0,"c":"Concurrent","k":1}
{"k":1,"c":"Concurrent","d":{},"p":0,"n":"Disturbance","m":"ConcurrentEA","t":1587139107.9942,"i":2}
{"m":"ConcurrentEA","n":"GenerationsStart","t":1587139108.193131,"d":{"distinct-elements":512,"population-size":512},"p":2,"c":"Events","k":0}
{"p":1,"d":{"population-size":512,"distinct-elements":512},"t":1587139108.193609,"m":"ConcurrentEA","n":"GenerationsStart","k":0,"c":"Events"}
{"c":"Events","k":0,"m":"ConcurrentEA","n":"Events","t":1587139112.526688,"d":{"id":4,"count":17,"best":25},"p":1}
{"c":"Events","k":0,"t":1587139112.554992,"m":"ConcurrentEA","n":"Generations","p":1,"d":{"individuals":9193,"generations":17}}
{"c":"Concurrent","k":2,"i":1,"t":1587139112.555583,"m":"ConcurrentEA","n":"Evolutionary"}
{"p":0,"d":{},"i":3,"t":1587139112.55614,"n":"Evolutionary","m":"ConcurrentEA","k":1,"c":"Concurrent"}
{"c":"Events","k":0,"n":"GenerationsStart","m":"ConcurrentEA","t":1587139112.642241,"d":{"population-size":512,"distinct-elements":512},"p":3}
{"d":{"id":6,"best":20,"count":25},"p":2,"n":"Events","m":"ConcurrentEA","t":1587139114.456006,"k":0,"c":"Events"}
{"c":"Concurrent","k":1,"n":"Mixer","m":"ConcurrentEA","i":4,"t":1587139114.480268,"d":{},"p":0}
{"c":"Events","k":0,"t":1587139114.481135,"m":"ConcurrentEA","n":"Generations","p":2,"d":{"generations":25,"individuals":13282}}
{"i":2,"t":1587139114.482929,"n":"Disturbance","m":"ConcurrentEA","k":2,"c":"Concurrent"}
{"i":4,"t":1587139114.484431,"n":"Mixer","m":"ConcurrentEA","k":2,"c":"Concurrent"}
{"p":0,"d":{},"i":5,"t":1587139114.484661,"n":"Disturbance","m":"ConcurrentEA","k":1,"c":"Concurrent"}
{"n":"GenerationsStart","m":"ConcurrentEA","t":1587139114.78992,"d":{"distinct-elements":512,"population-size":512},"p":5,"c":"Events","k":0}
{"c":"Events","k":0,"t":1587139116.896437,"m":"ConcurrentEA","n":"Events","p":3,"d":{"id":4,"count":17,"best":27}}
{"c":"Concurrent","k":1,"m":"ConcurrentEA","n":"Mixer","t":1587139116.916248,"i":6,"d":{},"p":0}
{"k":0,"c":"Events","p":3,"d":{"generations":17,"individuals":9196},"t":1587139116.917614,"m":"ConcurrentEA","n":"Generations"}
{"n":"Mixer","m":"ConcurrentEA","t":1587139116.917864,"i":6,"k":2,"c":"Concurrent"}
{"k":2,"c":"Concurrent","n":"Evolutionary","m":"ConcurrentEA","i":3,"t":1587139116.918105}
{"t":1587139116.918621,"i":7,"n":"Evolutionary","m":"ConcurrentEA","p":0,"d":{},"c":"Concurrent","k":1}
{"t":1587139117.225987,"m":"ConcurrentEA","n":"GenerationsStart","p":7,"d":{"population-size":512,"distinct-elements":512},"c":"Events","k":0}
{"d":{"id":6,"best":34,"count":25},"p":5,"m":"ConcurrentEA","n":"Events","t":1587139121.102296,"k":0,"c":"Events"}
{"c":"Concurrent","k":1,"m":"ConcurrentEA","n":"Mixer","t":1587139121.122235,"i":8,"d":{},"p":0}
{"c":"Events","k":0,"n":"Generations","m":"ConcurrentEA","t":1587139121.123404,"d":{"generations":25,"individuals":13273},"p":5}
{"k":2,"c":"Concurrent","i":8,"t":1587139121.123755,"n":"Mixer","m":"ConcurrentEA"}
{"n":"Disturbance","m":"ConcurrentEA","i":5,"t":1587139121.123762,"c":"Concurrent","k":2}
{"c":"Concurrent","k":1,"i":9,"t":1587139121.12729,"n":"Disturbance","m":"ConcurrentEA","p":0,"d":{}}
{"k":0,"c":"Events","p":9,"d":{"population-size":512,"distinct-elements":512},"t":1587139121.431696,"n":"GenerationsStart","m":"ConcurrentEA"}
{"k":0,"c":"Events","p":7,"d":{"id":4,"best":32,"count":17},"t":1587139121.608279,"m":"ConcurrentEA","n":"Events"}
{"c":"Concurrent","k":1,"t":1587139121.628966,"i":10,"m":"ConcurrentEA","n":"Mixer","p":0,"d":{}}
{"k":0,"c":"Events","p":7,"d":{"generations":17,"individuals":9190},"t":1587139121.62982,"n":"Generations","m":"ConcurrentEA"}
{"m":"ConcurrentEA","n":"Evolutionary","t":1587139121.630272,"i":7,"k":2,"c":"Concurrent"}
{"c":"Concurrent","k":2,"n":"Mixer","m":"ConcurrentEA","t":1587139121.630488,"i":10}
{"d":{},"p":0,"m":"ConcurrentEA","n":"Evolutionary","i":11,"t":1587139121.631056,"k":1,"c":"Concurrent"}
{"m":"ConcurrentEA","n":"GenerationsStart","t":1587139121.940068,"d":{"distinct-elements":512,"population-size":512},"p":11,"c":"Events","k":0}
{"c":"Events","k":0,"n":"Events","m":"ConcurrentEA","t":1587139126.338144,"d":{"id":4,"best":34,"count":17},"p":11}
{"c":"Concurrent","k":1,"n":"Mixer","m":"ConcurrentEA","i":12,"t":1587139126.357634,"d":{},"p":0}
{"k":0,"c":"Events","d":{"individuals":9189,"generations":17},"p":11,"n":"Generations","m":"ConcurrentEA","t":1587139126.361478}
{"k":2,"c":"Concurrent","m":"ConcurrentEA","n":"Evolutionary","i":11,"t":1587139126.361917}
{"c":"Concurrent","k":2,"i":12,"t":1587139126.361989,"m":"ConcurrentEA","n":"Mixer"}
{"k":1,"c":"Concurrent","d":{},"p":0,"m":"ConcurrentEA","n":"Evolutionary","i":13,"t":1587139126.362615}
{"k":0,"c":"Events","d":{"population-size":512,"distinct-elements":512},"p":13,"n":"GenerationsStart","m":"ConcurrentEA","t":1587139126.718358}
{"k":0,"c":"Events","p":9,"d":{"id":6,"count":25,"best":39},"t":1587139127.841932,"n":"Events","m":"ConcurrentEA"}
{"d":{},"p":0,"n":"Mixer","m":"ConcurrentEA","i":14,"t":1587139127.861872,"k":1,"c":"Concurrent"}
{"c":"Events","k":0,"m":"ConcurrentEA","n":"Generations","t":1587139127.863025,"d":{"individuals":13288,"generations":25},"p":9}
{"i":9,"t":1587139127.863409,"m":"ConcurrentEA","n":"Disturbance","k":2,"c":"Concurrent"}
{"m":"ConcurrentEA","n":"Mixer","t":1587139127.863741,"i":14,"c":"Concurrent","k":2}
{"k":1,"c":"Concurrent","p":0,"d":{},"t":1587139127.864151,"i":15,"n":"Disturbance","m":"ConcurrentEA"}
{"p":15,"d":{"distinct-elements":512,"population-size":512},"t":1587139128.178351,"n":"GenerationsStart","m":"ConcurrentEA","k":0,"c":"Events"}
{"c":"Events","k":0,"t":1587139131.123132,"n":"Events","m":"ConcurrentEA","p":13,"d":{"count":17,"best":37,"id":8}}
{"k":1,"c":"Concurrent","p":0,"d":{},"t":1587139131.143103,"i":16,"m":"ConcurrentEA","n":"Mixer"}
{"c":"Events","k":0,"t":1587139131.143766,"n":"Generations","m":"ConcurrentEA","p":13,"d":{"individuals":9187,"generations":17}}
{"k":2,"c":"Concurrent","n":"Evolutionary","m":"ConcurrentEA","i":13,"t":1587139131.144046}
{"m":"ConcurrentEA","n":"Mixer","i":16,"t":1587139131.14445,"k":2,"c":"Concurrent"}
{"c":"Concurrent","k":1,"n":"Evolutionary","m":"ConcurrentEA","i":17,"t":1587139131.144739,"d":{},"p":0}
{"k":0,"c":"Events","d":{"distinct-elements":512,"population-size":512},"p":17,"n":"GenerationsStart","m":"ConcurrentEA","t":1587139131.453355}
{"t":1587139134.6752,"m":"ConcurrentEA","n":"Events","p":15,"d":{"count":25,"best":44,"id":6},"c":"Events","k":0}
{"c":"Concurrent","k":1,"i":18,"t":1587139134.695413,"m":"ConcurrentEA","n":"Mixer","p":0,"d":{}}
{"d":{"generations":25,"individuals":13275},"p":15,"n":"Generations","m":"ConcurrentEA","t":1587139134.696613,"k":0,"c":"Events"}
{"i":18,"t":1587139134.696884,"m":"ConcurrentEA","n":"Mixer","c":"Concurrent","k":2}
{"k":2,"c":"Concurrent","m":"ConcurrentEA","n":"Disturbance","t":1587139134.697007,"i":15}
{"c":"Concurrent","k":1,"i":19,"t":1587139134.697486,"m":"ConcurrentEA","n":"Disturbance","p":0,"d":{}}
{"k":0,"c":"Events","d":{"population-size":512,"distinct-elements":512},"p":19,"n":"GenerationsStart","m":"ConcurrentEA","t":1587139135.009497}
{"k":0,"c":"Events","p":17,"d":{"id":8,"count":17,"best":44},"t":1587139135.847856,"n":"Events","m":"ConcurrentEA"}
{"m":"ConcurrentEA","n":"Mixer","t":1587139135.867764,"i":20,"d":{},"p":0,"c":"Concurrent","k":1}
{"p":17,"d":{"individuals":9185,"generations":17},"t":1587139135.868478,"m":"ConcurrentEA","n":"Generations","k":0,"c":"Events"}
{"t":1587139135.86889,"i":17,"m":"ConcurrentEA","n":"Evolutionary","c":"Concurrent","k":2}
{"m":"ConcurrentEA","n":"Mixer","t":1587139135.869213,"i":20,"c":"Concurrent","k":2}
{"d":{},"p":0,"n":"Evolutionary","m":"ConcurrentEA","i":21,"t":1587139135.86965,"k":1,"c":"Concurrent"}
{"t":1587139136.175313,"n":"GenerationsStart","m":"ConcurrentEA","p":21,"d":{"population-size":512,"distinct-elements":512},"c":"Events","k":0}
{"d":{"id":8,"count":17,"best":48},"p":21,"m":"ConcurrentEA","n":"Events","t":1587139140.61079,"k":0,"c":"Events"}
{"c":"Concurrent","k":1,"m":"ConcurrentEA","n":"Mixer","i":22,"t":1587139140.636097,"d":{},"p":0}
{"p":21,"d":{"individuals":9188,"generations":17},"t":1587139140.636461,"m":"ConcurrentEA","n":"Generations","k":0,"c":"Events"}
{"n":"Evolutionary","m":"ConcurrentEA","i":21,"t":1587139140.636861,"k":2,"c":"Concurrent"}
{"c":"Concurrent","k":1,"i":23,"t":1587139140.638028,"n":"Evolutionary","m":"ConcurrentEA","p":0,"d":{}}
{"i":22,"t":1587139140.637973,"n":"Mixer","m":"ConcurrentEA","k":2,"c":"Concurrent"}
{"p":23,"d":{"distinct-elements":512,"population-size":512},"t":1587139140.990419,"n":"GenerationsStart","m":"ConcurrentEA","k":0,"c":"Events"}
{"t":1587139141.484239,"n":"Events","m":"ConcurrentEA","p":19,"d":{"id":4,"count":25,"best":44},"c":"Events","k":0}
{"d":{},"p":0,"m":"ConcurrentEA","n":"Mixer","i":24,"t":1587139141.503753,"k":1,"c":"Concurrent"}
{"k":2,"c":"Concurrent","t":1587139141.50568,"i":24,"m":"ConcurrentEA","n":"Mixer"}
{"c":"Events","k":0,"m":"ConcurrentEA","n":"Generations","t":1587139141.50566,"d":{"generations":25,"individuals":13269},"p":19}
{"t":1587139141.506017,"i":19,"m":"ConcurrentEA","n":"Disturbance","k":2,"c":"Concurrent"}
{"k":1,"c":"Concurrent","p":0,"d":{},"i":25,"t":1587139141.506555,"m":"ConcurrentEA","n":"Disturbance"}
{"k":0,"c":"Events","p":25,"d":{"population-size":512,"distinct-elements":512},"t":1587139141.813259,"m":"ConcurrentEA","n":"GenerationsStart"}
{"k":0,"c":"Events","p":23,"d":{"best":44,"count":17,"id":8},"t":1587139145.426804,"m":"ConcurrentEA","n":"Events"}
{"n":"Mixer","m":"ConcurrentEA","i":26,"t":1587139145.446621,"d":{},"p":0,"c":"Concurrent","k":1}
{"n":"Generations","m":"ConcurrentEA","t":1587139145.44733,"d":{"generations":17,"individuals":9184},"p":23,"c":"Events","k":0}
{"n":"Evolutionary","m":"ConcurrentEA","t":1587139145.447592,"i":23,"c":"Concurrent","k":2}
{"k":2,"c":"Concurrent","m":"ConcurrentEA","n":"Mixer","t":1587139145.44796,"i":26}
{"t":1587139145.44825,"i":27,"m":"ConcurrentEA","n":"Evolutionary","p":0,"d":{},"c":"Concurrent","k":1}
{"t":1587139145.756595,"m":"ConcurrentEA","n":"GenerationsStart","p":27,"d":{"population-size":512,"distinct-elements":512},"c":"Events","k":0}
{"k":0,"c":"Events","p":25,"d":{"id":6,"best":47,"count":25},"t":1587139148.266289,"n":"Events","m":"ConcurrentEA"}
{"p":0,"d":{},"t":1587139148.286634,"i":28,"m":"ConcurrentEA","n":"Mixer","k":1,"c":"Concurrent"}
{"m":"ConcurrentEA","n":"Mixer","i":28,"t":1587139148.288027,"k":2,"c":"Concurrent"}
{"c":"Events","k":0,"t":1587139148.287938,"n":"Generations","m":"ConcurrentEA","p":25,"d":{"individuals":13273,"generations":25}}
{"t":1587139148.288326,"i":25,"n":"Disturbance","m":"ConcurrentEA","k":2,"c":"Concurrent"}
{"p":0,"d":{},"i":29,"t":1587139148.288776,"n":"Disturbance","m":"ConcurrentEA","k":1,"c":"Concurrent"}
{"k":0,"c":"Events","d":{"distinct-elements":512,"population-size":512},"p":29,"m":"ConcurrentEA","n":"GenerationsStart","t":1587139148.608284}
{"t":1587139150.133811,"m":"ConcurrentEA","n":"Events","p":27,"d":{"best":49,"count":17,"id":8},"c":"Events","k":0}
{"c":"Concurrent","k":1,"t":1587139150.15493,"i":30,"n":"Mixer","m":"ConcurrentEA","p":0,"d":{}}
{"t":1587139150.155575,"n":"Generations","m":"ConcurrentEA","p":27,"d":{"individuals":9181,"generations":17},"c":"Events","k":0}
{"m":"ConcurrentEA","n":"Evolutionary","i":27,"t":1587139150.155949,"c":"Concurrent","k":2}
{"c":"Concurrent","k":2,"t":1587139150.156311,"i":30,"m":"ConcurrentEA","n":"Mixer"}
{"n":"Evolutionary","m":"ConcurrentEA","t":1587139150.156691,"i":31,"d":{},"p":0,"c":"Concurrent","k":1}
{"d":{"distinct-elements":512,"population-size":512},"p":31,"n":"GenerationsStart","m":"ConcurrentEA","t":1587139150.47467,"k":0,"c":"Events"}
{"n":"Events","m":"ConcurrentEA","t":1587139154.874108,"d":{"best":46,"count":17,"id":8},"p":31,"c":"Events","k":0}
{"k":1,"c":"Concurrent","d":{},"p":0,"m":"ConcurrentEA","n":"Mixer","t":1587139154.893557,"i":32}
{"d":{"individuals":9184,"generations":17},"p":31,"m":"ConcurrentEA","n":"Generations","t":1587139154.894437,"k":0,"c":"Events"}
{"m":"ConcurrentEA","n":"Evolutionary","t":1587139154.894714,"i":31,"c":"Concurrent","k":2}
{"c":"Concurrent","k":2,"m":"ConcurrentEA","n":"Mixer","t":1587139154.894852,"i":32}
{"i":33,"t":1587139154.898939,"n":"Evolutionary","m":"ConcurrentEA","p":0,"d":{},"c":"Concurrent","k":1}
{"k":0,"c":"Events","p":29,"d":{"id":4,"best":49,"count":25},"t":1587139155.110007,"n":"Events","m":"ConcurrentEA"}
{"n":"Mixer","m":"ConcurrentEA","i":34,"t":1587139155.126406,"d":{},"p":0,"c":"Concurrent","k":1}
{"i":34,"t":1587139155.131923,"n":"Mixer","m":"ConcurrentEA","c":"Concurrent","k":2}
{"c":"Events","k":0,"t":1587139155.13172,"n":"Generations","m":"ConcurrentEA","p":29,"d":{"generations":25,"individuals":13257}}
{"k":2,"c":"Concurrent","i":29,"t":1587139155.133378,"m":"ConcurrentEA","n":"Disturbance"}
{"p":0,"d":{},"t":1587139155.133852,"i":35,"n":"Disturbance","m":"ConcurrentEA","k":1,"c":"Concurrent"}
{"k":0,"c":"Events","d":{"population-size":512,"distinct-elements":512},"p":33,"m":"ConcurrentEA","n":"GenerationsStart","t":1587139155.204965}
{"d":{"distinct-elements":512,"population-size":512},"p":35,"n":"GenerationsStart","m":"ConcurrentEA","t":1587139155.441786,"k":0,"c":"Events"}
{"k":0,"c":"Events","p":33,"d":{"best":49,"count":17,"id":6},"t":1587139159.677298,"m":"ConcurrentEA","n":"Events"}
{"c":"Concurrent","k":1,"t":1587139159.701764,"i":36,"n":"Mixer","m":"ConcurrentEA","p":0,"d":{}}
{"p":33,"d":{"individuals":9188,"generations":17},"t":1587139159.702376,"n":"Generations","m":"ConcurrentEA","k":0,"c":"Events"}
{"c":"Concurrent","k":2,"i":33,"t":1587139159.702758,"m":"ConcurrentEA","n":"Evolutionary"}
{"c":"Concurrent","k":2,"n":"Mixer","m":"ConcurrentEA","i":36,"t":1587139159.703097}
{"c":"Concurrent","k":1,"i":37,"t":1587139159.703468,"n":"Evolutionary","m":"ConcurrentEA","p":0,"d":{}}
{"c":"Events","k":0,"t":1587139160.05909,"m":"ConcurrentEA","n":"GenerationsStart","p":37,"d":{"distinct-elements":512,"population-size":512}}
{"c":"Events","k":0,"t":1587139162.002571,"n":"Events","m":"ConcurrentEA","p":35,"d":{"id":8,"count":25,"best":52}}
{"k":1,"c":"Concurrent","d":{},"p":0,"n":"Mixer","m":"ConcurrentEA","i":38,"t":1587139162.022375}
{"k":2,"c":"Concurrent","n":"Mixer","m":"ConcurrentEA","t":1587139162.023681,"i":38}
{"k":0,"c":"Events","p":35,"d":{"individuals":13272,"generations":25},"t":1587139162.023672,"n":"Generations","m":"ConcurrentEA"}
{"i":35,"t":1587139162.023951,"n":"Disturbance","m":"ConcurrentEA","k":2,"c":"Concurrent"}
{"d":{},"p":0,"n":"Disturbance","m":"ConcurrentEA","i":39,"t":1587139162.024376,"k":1,"c":"Concurrent"}
{"k":0,"c":"Events","d":{"distinct-elements":512,"population-size":512},"p":39,"m":"ConcurrentEA","n":"GenerationsStart","t":1587139162.382212}
{"c":"Events","k":0,"t":1587139164.521661,"m":"ConcurrentEA","n":"Events","p":37,"d":{"id":6,"count":17,"best":51}}
{"d":{},"p":0,"m":"ConcurrentEA","n":"Mixer","t":1587139164.541395,"i":40,"k":1,"c":"Concurrent"}
{"t":1587139164.542208,"m":"ConcurrentEA","n":"Generations","p":37,"d":{"individuals":9184,"generations":17},"c":"Events","k":0}
{"c":"Concurrent","k":2,"n":"Evolutionary","m":"ConcurrentEA","t":1587139164.542579,"i":37}
{"k":2,"c":"Concurrent","i":40,"t":1587139164.542687,"n":"Mixer","m":"ConcurrentEA"}
{"k":1,"c":"Concurrent","p":0,"d":{},"i":41,"t":1587139164.543147,"n":"Evolutionary","m":"ConcurrentEA"}
{"n":"GenerationsStart","m":"ConcurrentEA","t":1587139164.852362,"d":{"distinct-elements":511,"population-size":512},"p":41,"c":"Events","k":0}
{"d":{"id":4,"best":52,"count":25},"p":39,"n":"Events","m":"ConcurrentEA","t":1587139168.895228,"k":0,"c":"Events"}
{"t":1587139168.915745,"i":42,"n":"Mixer","m":"ConcurrentEA","p":0,"d":{},"c":"Concurrent","k":1}
{"d":{"individuals":13262,"generations":25},"p":39,"n":"Generations","m":"ConcurrentEA","t":1587139168.916788,"k":0,"c":"Events"}
{"m":"ConcurrentEA","n":"Mixer","t":1587139168.917085,"i":42,"k":2,"c":"Concurrent"}
{"k":2,"c":"Concurrent","n":"Disturbance","m":"ConcurrentEA","i":39,"t":1587139168.917148}
{"c":"Concurrent","k":1,"n":"Disturbance","m":"ConcurrentEA","t":1587139168.917626,"i":43,"d":{},"p":0}
{"k":0,"c":"Events","p":41,"d":{"id":8,"best":54,"count":17},"t":1587139169.227754,"m":"ConcurrentEA","n":"Events"}
{"p":43,"d":{"population-size":512,"distinct-elements":512},"t":1587139169.228037,"m":"ConcurrentEA","n":"GenerationsStart","k":0,"c":"Events"}
{"p":0,"d":{},"t":1587139169.246696,"i":44,"n":"Mixer","m":"ConcurrentEA","k":1,"c":"Concurrent"}
{"d":{"individuals":9185,"generations":17},"p":41,"m":"ConcurrentEA","n":"Generations","t":1587139169.250411,"k":0,"c":"Events"}
{"t":1587139169.251098,"i":41,"m":"ConcurrentEA","n":"Evolutionary","c":"Concurrent","k":2}
{"m":"ConcurrentEA","n":"Mixer","i":44,"t":1587139169.251164,"c":"Concurrent","k":2}
{"k":1,"c":"Concurrent","d":{},"p":0,"m":"ConcurrentEA","n":"Evolutionary","t":1587139169.251746,"i":45}
{"c":"Events","k":0,"m":"ConcurrentEA","n":"GenerationsStart","t":1587139169.557229,"d":{"population-size":512,"distinct-elements":512},"p":45}
{"k":0,"c":"Events","p":45,"d":{"best":56,"count":17,"id":8},"t":1587139173.983743,"n":"Events","m":"ConcurrentEA"}
{"m":"ConcurrentEA","n":"Mixer","i":46,"t":1587139174.00355,"d":{},"p":0,"c":"Concurrent","k":1}
{"d":{"individuals":9187,"generations":17},"p":45,"n":"Generations","m":"ConcurrentEA","t":1587139174.004211,"k":0,"c":"Events"}
{"k":2,"c":"Concurrent","t":1587139174.004566,"i":45,"m":"ConcurrentEA","n":"Evolutionary"}
{"c":"Concurrent","k":2,"t":1587139174.00491,"i":46,"m":"ConcurrentEA","n":"Mixer"}
{"p":0,"d":{},"t":1587139174.005268,"i":47,"n":"Evolutionary","m":"ConcurrentEA","k":1,"c":"Concurrent"}
{"d":{"distinct-elements":512,"population-size":512},"p":47,"m":"ConcurrentEA","n":"GenerationsStart","t":1587139174.318968,"k":0,"c":"Events"}
{"c":"Events","k":0,"n":"Events","m":"ConcurrentEA","t":1587139175.747316,"d":{"id":6,"count":25,"best":53},"p":43}
{"c":"Concurrent","k":1,"n":"Mixer","m":"ConcurrentEA","t":1587139175.766851,"i":48,"d":{},"p":0}
{"i":48,"t":1587139175.771562,"m":"ConcurrentEA","n":"Mixer","c":"Concurrent","k":2}
{"c":"Events","k":0,"m":"ConcurrentEA","n":"Generations","t":1587139175.771644,"d":{"generations":25,"individuals":13261},"p":43}
{"k":2,"c":"Concurrent","i":43,"t":1587139175.771978,"m":"ConcurrentEA","n":"Disturbance"}
{"d":{},"p":0,"n":"Disturbance","m":"ConcurrentEA","i":49,"t":1587139175.77239,"k":1,"c":"Concurrent"}
{"k":0,"c":"Events","d":{"population-size":512,"distinct-elements":512},"p":49,"n":"GenerationsStart","m":"ConcurrentEA","t":1587139176.080344}
{"k":0,"c":"Events","p":47,"d":{"best":49,"count":17,"id":8},"t":1587139178.75774,"n":"Events","m":"ConcurrentEA"}
{"k":1,"c":"Concurrent","d":{},"p":0,"m":"ConcurrentEA","n":"Mixer","i":50,"t":1587139178.777567}
{"k":0,"c":"Events","p":47,"d":{"generations":17,"individuals":9174},"t":1587139178.778252,"n":"Generations","m":"ConcurrentEA"}
{"n":"Evolutionary","m":"ConcurrentEA","t":1587139178.778624,"i":47,"c":"Concurrent","k":2}
{"c":"Concurrent","k":2,"n":"Mixer","m":"ConcurrentEA","t":1587139178.778846,"i":50}
{"c":"Concurrent","k":1,"n":"Evolutionary","m":"ConcurrentEA","i":51,"t":1587139178.779249,"d":{},"p":0}
{"k":0,"c":"Events","d":{"population-size":512,"distinct-elements":512},"p":51,"n":"GenerationsStart","m":"ConcurrentEA","t":1587139179.08402}
{"c":"Events","k":0,"t":1587139182.578606,"m":"ConcurrentEA","n":"Events","p":49,"d":{"best":50,"count":25,"id":4}}
{"m":"ConcurrentEA","n":"Mixer","i":52,"t":1587139182.598884,"d":{},"p":0,"c":"Concurrent","k":1}
{"i":52,"t":1587139182.600102,"m":"ConcurrentEA","n":"Mixer","k":2,"c":"Concurrent"}
{"c":"Events","k":0,"m":"ConcurrentEA","n":"Generations","t":1587139182.600074,"d":{"generations":25,"individuals":13261},"p":49}
{"n":"Disturbance","m":"ConcurrentEA","t":1587139182.600357,"i":49,"k":2,"c":"Concurrent"}
{"p":0,"d":{},"t":1587139182.600753,"i":53,"n":"Disturbance","m":"ConcurrentEA","k":1,"c":"Concurrent"}
{"n":"GenerationsStart","m":"ConcurrentEA","t":1587139182.905517,"d":{"population-size":512,"distinct-elements":512},"p":53,"c":"Events","k":0}
{"k":0,"c":"Events","d":{"count":17,"best":55,"id":6},"p":51,"m":"ConcurrentEA","n":"Events","t":1587139183.521581}
{"m":"ConcurrentEA","n":"Mixer","t":1587139183.541656,"i":54,"d":{},"p":0,"c":"Concurrent","k":1}
{"t":1587139183.542334,"n":"Generations","m":"ConcurrentEA","p":51,"d":{"generations":17,"individuals":9181},"c":"Events","k":0}
{"k":2,"c":"Concurrent","i":51,"t":1587139183.542625,"n":"Evolutionary","m":"ConcurrentEA"}
{"n":"Mixer","m":"ConcurrentEA","t":1587139183.542923,"i":54,"k":2,"c":"Concurrent"}
{"c":"Concurrent","k":1,"n":"Evolutionary","m":"ConcurrentEA","t":1587139183.543294,"i":55,"d":{},"p":0}
{"k":0,"c":"Events","d":{"distinct-elements":512,"population-size":512},"p":55,"m":"ConcurrentEA","n":"GenerationsStart","t":1587139183.855217}
{"d":{"count":17,"best":53,"id":6},"p":55,"n":"Events","m":"ConcurrentEA","t":1587139188.340216,"k":0,"c":"Events"}
{"t":1587139188.359894,"i":56,"n":"Mixer","m":"ConcurrentEA","p":0,"d":{},"c":"Concurrent","k":1}
{"t":1587139188.360528,"n":"Generations","m":"ConcurrentEA","p":55,"d":{"individuals":9181,"generations":17},"c":"Events","k":0}
{"k":2,"c":"Concurrent","m":"ConcurrentEA","n":"Evolutionary","i":55,"t":1587139188.360847}
{"k":2,"c":"Concurrent","n":"Mixer","m":"ConcurrentEA","t":1587139188.361165,"i":56}
{"c":"Concurrent","k":1,"m":"ConcurrentEA","n":"Evolutionary","t":1587139188.361506,"i":57,"d":{},"p":0}
{"n":"GenerationsStart","m":"ConcurrentEA","t":1587139188.677178,"d":{"population-size":512,"distinct-elements":512},"p":57,"c":"Events","k":0}
{"k":0,"c":"Events","d":{"id":8,"count":25,"best":52},"p":53,"m":"ConcurrentEA","n":"Events","t":1587139189.424727}
{"d":{},"p":0,"n":"Mixer","m":"ConcurrentEA","t":1587139189.444672,"i":58,"k":1,"c":"Concurrent"}
{"i":58,"t":1587139189.445851,"n":"Mixer","m":"ConcurrentEA","c":"Concurrent","k":2}
{"c":"Events","k":0,"t":1587139189.445872,"n":"Generations","m":"ConcurrentEA","p":53,"d":{"generations":25,"individuals":13267}}
{"i":53,"t":1587139189.446097,"n":"Disturbance","m":"ConcurrentEA","c":"Concurrent","k":2}
{"d":{},"p":0,"n":"Disturbance","m":"ConcurrentEA","i":59,"t":1587139189.446452,"k":1,"c":"Concurrent"}
{"p":59,"d":{"distinct-elements":512,"population-size":512},"t":1587139189.762399,"n":"GenerationsStart","m":"ConcurrentEA","k":0,"c":"Events"}
{"c":"Events","k":0,"t":1587139193.153043,"n":"Events","m":"ConcurrentEA","p":57,"d":{"id":6,"count":17,"best":55}}
{"p":0,"d":{},"i":60,"t":1587139193.172471,"n":"Mixer","m":"ConcurrentEA","k":1,"c":"Concurrent"}
{"k":0,"c":"Events","d":{"generations":17,"individuals":9172},"p":57,"n":"Generations","m":"ConcurrentEA","t":1587139193.173278}
{"k":2,"c":"Concurrent","t":1587139193.173581,"i":57,"m":"ConcurrentEA","n":"Evolutionary"}
{"k":2,"c":"Concurrent","m":"ConcurrentEA","n":"Mixer","i":60,"t":1587139193.173712}
{"m":"ConcurrentEA","n":"Evolutionary","t":1587139193.174101,"i":61,"d":{},"p":0,"c":"Concurrent","k":1}
{"p":61,"d":{"population-size":512,"distinct-elements":512},"t":1587139193.480621,"m":"ConcurrentEA","n":"GenerationsStart","k":0,"c":"Events"}
{"k":0,"c":"Events","p":59,"d":{"best":52,"count":25,"id":4},"t":1587139196.345154,"n":"Events","m":"ConcurrentEA"}
{"d":{},"p":0,"m":"ConcurrentEA","n":"Mixer","i":62,"t":1587139196.364821,"k":1,"c":"Concurrent"}
{"k":0,"c":"Events","p":59,"d":{"individuals":13276,"generations":25},"t":1587139196.365809,"n":"Generations","m":"ConcurrentEA"}
{"i":62,"t":1587139196.366097,"m":"ConcurrentEA","n":"Mixer","k":2,"c":"Concurrent"}
{"m":"ConcurrentEA","n":"Disturbance","i":59,"t":1587139196.366109,"k":2,"c":"Concurrent"}
{"n":"Disturbance","m":"ConcurrentEA","i":63,"t":1587139196.366603,"d":{},"p":0,"c":"Concurrent","k":1}
{"c":"Events","k":0,"t":1587139196.674033,"n":"GenerationsStart","m":"ConcurrentEA","p":63,"d":{"population-size":512,"distinct-elements":512}}
{"d":{"best":51,"count":17,"id":8},"p":61,"n":"Events","m":"ConcurrentEA","t":1587139197.910448,"k":0,"c":"Events"}
{"n":"Mixer","m":"ConcurrentEA","t":1587139197.930757,"i":64,"d":{},"p":0,"c":"Concurrent","k":1}
{"c":"Events","k":0,"n":"Generations","m":"ConcurrentEA","t":1587139197.931681,"d":{"generations":17,"individuals":9184},"p":61}
{"k":2,"c":"Concurrent","m":"ConcurrentEA","n":"Evolutionary","t":1587139197.931973,"i":61}
{"t":1587139197.932133,"i":64,"n":"Mixer","m":"ConcurrentEA","k":2,"c":"Concurrent"}
{"d":{},"p":0,"m":"ConcurrentEA","n":"Evolutionary","i":65,"t":1587139197.936665,"k":1,"c":"Concurrent"}
{"n":"GenerationsStart","m":"ConcurrentEA","t":1587139198.293351,"d":{"distinct-elements":512,"population-size":512},"p":65,"c":"Events","k":0}
{"d":{"count":17,"best":53,"id":8},"p":65,"m":"ConcurrentEA","n":"Events","t":1587139202.786888,"k":0,"c":"Events"}
{"d":{},"p":0,"n":"Mixer","m":"ConcurrentEA","i":66,"t":1587139202.809738,"k":1,"c":"Concurrent"}
{"t":1587139202.81042,"m":"ConcurrentEA","n":"Generations","p":65,"d":{"individuals":9174,"generations":17},"c":"Events","k":0}
{"c":"Concurrent","k":2,"t":1587139202.810722,"i":65,"m":"ConcurrentEA","n":"Evolutionary"}
{"c":"Concurrent","k":2,"m":"ConcurrentEA","n":"Mixer","i":66,"t":1587139202.810972}
{"k":1,"c":"Concurrent","p":0,"d":{},"t":1587139202.811364,"i":67,"m":"ConcurrentEA","n":"Evolutionary"}
{"n":"GenerationsStart","m":"ConcurrentEA","t":1587139203.121257,"d":{"population-size":512,"distinct-elements":512},"p":67,"c":"Events","k":0}
{"c":"Events","k":0,"n":"Events","m":"ConcurrentEA","t":1587139203.212905,"d":{"best":56,"count":25,"id":6},"p":63}
{"k":1,"c":"Concurrent","p":0,"d":{},"i":68,"t":1587139203.233004,"n":"Mixer","m":"ConcurrentEA"}
{"c":"Concurrent","k":2,"t":1587139203.23423,"i":68,"n":"Mixer","m":"ConcurrentEA"}
{"m":"ConcurrentEA","n":"Generations","t":1587139203.234368,"d":{"individuals":13268,"generations":25},"p":63,"c":"Events","k":0}
{"n":"Disturbance","m":"ConcurrentEA","t":1587139203.234592,"i":63,"k":2,"c":"Concurrent"}
{"k":1,"c":"Concurrent","p":0,"d":{},"t":1587139203.23496,"i":69,"n":"Disturbance","m":"ConcurrentEA"}
{"k":0,"c":"Events","p":69,"d":{"distinct-elements":512,"population-size":512},"t":1587139203.541257,"m":"ConcurrentEA","n":"GenerationsStart"}
{"c":"Events","k":0,"m":"ConcurrentEA","n":"Events","t":1587139207.532731,"d":{"count":17,"best":49,"id":8},"p":67}
{"m":"ConcurrentEA","n":"Mixer","t":1587139207.552602,"i":70,"d":{},"p":0,"c":"Concurrent","k":1}
{"t":1587139207.553269,"m":"ConcurrentEA","n":"Generations","p":67,"d":{"generations":17,"individuals":9188},"c":"Events","k":0}
{"k":2,"c":"Concurrent","n":"Evolutionary","m":"ConcurrentEA","t":1587139207.553576,"i":67}
{"t":1587139207.553818,"i":70,"m":"ConcurrentEA","n":"Mixer","k":2,"c":"Concurrent"}
{"i":71,"t":1587139207.554167,"m":"ConcurrentEA","n":"Evolutionary","p":0,"d":{},"c":"Concurrent","k":1}
{"p":71,"d":{"population-size":512,"distinct-elements":512},"t":1587139207.86754,"m":"ConcurrentEA","n":"GenerationsStart","k":0,"c":"Events"}
{"k":0,"c":"Events","d":{"id":4,"count":25,"best":50},"p":69,"m":"ConcurrentEA","n":"Events","t":1587139210.127106}
{"d":{},"p":0,"n":"Mixer","m":"ConcurrentEA","t":1587139210.151711,"i":72,"k":1,"c":"Concurrent"}
{"k":2,"c":"Concurrent","i":72,"t":1587139210.152949,"m":"ConcurrentEA","n":"Mixer"}
{"k":0,"c":"Events","p":69,"d":{"individuals":13274,"generations":25},"t":1587139210.153032,"m":"ConcurrentEA","n":"Generations"}
{"m":"ConcurrentEA","n":"Disturbance","t":1587139210.153336,"i":69,"k":2,"c":"Concurrent"}
{"c":"Concurrent","k":1,"n":"Disturbance","m":"ConcurrentEA","t":1587139210.153722,"i":73,"d":{},"p":0}
{"k":0,"c":"Events","d":{"population-size":512,"distinct-elements":512},"p":73,"n":"GenerationsStart","m":"ConcurrentEA","t":1587139210.461597}
{"k":0,"c":"Events","d":{"count":17,"best":49,"id":6},"p":71,"m":"ConcurrentEA","n":"Events","t":1587139212.350701}
{"c":"Concurrent","k":1,"m":"ConcurrentEA","n":"Mixer","t":1587139212.370425,"i":74,"d":{},"p":0}
{"m":"ConcurrentEA","n":"Generations","t":1587139212.37108,"d":{"generations":17,"individuals":9190},"p":71,"c":"Events","k":0}
{"k":2,"c":"Concurrent","i":71,"t":1587139212.371394,"m":"ConcurrentEA","n":"Evolutionary"}
{"n":"Mixer","m":"ConcurrentEA","t":1587139212.371655,"i":74,"c":"Concurrent","k":2}
{"p":0,"d":{},"t":1587139212.372017,"i":75,"n":"Evolutionary","m":"ConcurrentEA","k":1,"c":"Concurrent"}
{"t":1587139212.68325,"n":"GenerationsStart","m":"ConcurrentEA","p":75,"d":{"distinct-elements":512,"population-size":512},"c":"Events","k":0}
{"t":1587139216.989919,"n":"Events","m":"ConcurrentEA","p":73,"d":{"best":57,"count":25,"id":8},"c":"Events","k":0}
{"k":1,"c":"Concurrent","d":{},"p":0,"n":"Mixer","m":"ConcurrentEA","i":76,"t":1587139217.009943}
{"m":"ConcurrentEA","n":"Mixer","t":1587139217.011144,"i":76,"c":"Concurrent","k":2}
{"c":"Events","k":0,"m":"ConcurrentEA","n":"Generations","t":1587139217.01132,"d":{"individuals":13259,"generations":25},"p":73}
{"c":"Concurrent","k":2,"n":"Disturbance","m":"ConcurrentEA","i":73,"t":1587139217.011601}
{"d":{},"p":0,"m":"ConcurrentEA","n":"Disturbance","t":1587139217.01196,"i":77,"k":1,"c":"Concurrent"}
{"p":75,"d":{"id":6,"count":17,"best":51},"t":1587139217.154663,"n":"Events","m":"ConcurrentEA","k":0,"c":"Events"}
{"c":"Concurrent","k":1,"i":78,"t":1587139217.176051,"n":"Mixer","m":"ConcurrentEA","p":0,"d":{}}
{"n":"Generations","m":"ConcurrentEA","t":1587139217.176788,"d":{"individuals":9175,"generations":17},"p":75,"c":"Events","k":0}
{"c":"Concurrent","k":2,"i":75,"t":1587139217.177079,"m":"ConcurrentEA","n":"Evolutionary"}
{"m":"ConcurrentEA","n":"Mixer","i":78,"t":1587139217.177283,"k":2,"c":"Concurrent"}
{"i":79,"t":1587139217.177665,"m":"ConcurrentEA","n":"Evolutionary","p":0,"d":{},"c":"Concurrent","k":1}
{"k":0,"c":"Events","d":{"distinct-elements":512,"population-size":512},"p":77,"n":"GenerationsStart","m":"ConcurrentEA","t":1587139217.325322}
{"k":0,"c":"Events","d":{"population-size":512,"distinct-elements":512},"p":79,"m":"ConcurrentEA","n":"GenerationsStart","t":1587139217.484199}
{"n":"Events","m":"ConcurrentEA","t":1587139221.937495,"d":{"id":8,"best":50,"count":17},"p":79,"c":"Events","k":0}
{"i":80,"t":1587139221.957638,"m":"ConcurrentEA","n":"Mixer","p":0,"d":{},"c":"Concurrent","k":1}
{"t":1587139221.958363,"n":"Generations","m":"ConcurrentEA","p":79,"d":{"individuals":9180,"generations":17},"c":"Events","k":0}
{"m":"ConcurrentEA","n":"Evolutionary","i":79,"t":1587139221.958571,"c":"Concurrent","k":2}
{"t":1587139221.958849,"i":80,"n":"Mixer","m":"ConcurrentEA","k":2,"c":"Concurrent"}
{"p":0,"d":{},"i":81,"t":1587139221.959121,"n":"Evolutionary","m":"ConcurrentEA","k":1,"c":"Concurrent"}
{"c":"Events","k":0,"t":1587139222.265918,"m":"ConcurrentEA","n":"GenerationsStart","p":81,"d":{"distinct-elements":512,"population-size":512}}
{"c":"Events","k":0,"t":1587139223.940853,"m":"ConcurrentEA","n":"Events","p":77,"d":{"id":4,"count":25,"best":49}}
{"k":1,"c":"Concurrent","d":{},"p":0,"m":"ConcurrentEA","n":"Mixer","i":82,"t":1587139223.961108}
{"i":82,"t":1587139223.962314,"m":"ConcurrentEA","n":"Mixer","c":"Concurrent","k":2}
{"k":0,"c":"Events","p":77,"d":{"individuals":13259,"generations":25},"t":1587139223.962389,"m":"ConcurrentEA","n":"Generations"}
{"n":"Disturbance","m":"ConcurrentEA","i":77,"t":1587139223.962689,"k":2,"c":"Concurrent"}
{"p":0,"d":{},"t":1587139223.963061,"i":83,"n":"Disturbance","m":"ConcurrentEA","k":1,"c":"Concurrent"}
{"p":83,"d":{"population-size":512,"distinct-elements":512},"t":1587139224.272688,"m":"ConcurrentEA","n":"GenerationsStart","k":0,"c":"Events"}
{"c":"Events","k":0,"m":"ConcurrentEA","n":"Events","t":1587139226.700519,"d":{"best":54,"count":17,"id":8},"p":81}
{"d":{},"p":0,"n":"Mixer","m":"ConcurrentEA","i":84,"t":1587139226.720209,"k":1,"c":"Concurrent"}
{"c":"Events","k":0,"n":"Generations","m":"ConcurrentEA","t":1587139226.724265,"d":{"individuals":9175,"generations":17},"p":81}
{"k":2,"c":"Concurrent","m":"ConcurrentEA","n":"Evolutionary","t":1587139226.724621,"i":81}
{"i":84,"t":1587139226.724693,"n":"Mixer","m":"ConcurrentEA","c":"Concurrent","k":2}
{"k":1,"c":"Concurrent","d":{},"p":0,"n":"Evolutionary","m":"ConcurrentEA","t":1587139226.725217,"i":85}
{"k":0,"c":"Events","p":85,"d":{"distinct-elements":512,"population-size":512},"t":1587139227.028393,"n":"GenerationsStart","m":"ConcurrentEA"}
{"k":0,"c":"Events","d":{"count":25,"best":49,"id":6},"p":83,"n":"Events","m":"ConcurrentEA","t":1587139230.810487}
{"p":0,"d":{},"t":1587139230.831002,"i":86,"m":"ConcurrentEA","n":"Mixer","k":1,"c":"Concurrent"}
{"k":2,"c":"Concurrent","m":"ConcurrentEA","n":"Mixer","i":86,"t":1587139230.832195}
{"c":"Events","k":0,"m":"ConcurrentEA","n":"Generations","t":1587139230.832408,"d":{"generations":25,"individuals":13262},"p":83}
{"m":"ConcurrentEA","n":"Disturbance","t":1587139230.832636,"i":83,"c":"Concurrent","k":2}
{"c":"Concurrent","k":1,"i":87,"t":1587139230.832998,"n":"Disturbance","m":"ConcurrentEA","p":0,"d":{}}
{"n":"GenerationsStart","m":"ConcurrentEA","t":1587139231.151803,"d":{"distinct-elements":512,"population-size":512},"p":87,"c":"Events","k":0}
{"c":"Events","k":0,"t":1587139231.494855,"m":"ConcurrentEA","n":"Events","p":85,"d":{"count":17,"best":52,"id":8}}
{"t":1587139231.514723,"i":88,"m":"ConcurrentEA","n":"Mixer","p":0,"d":{},"c":"Concurrent","k":1}
{"d":{"individuals":9183,"generations":17},"p":85,"m":"ConcurrentEA","n":"Generations","t":1587139231.515397,"k":0,"c":"Events"}
{"c":"Concurrent","k":2,"m":"ConcurrentEA","n":"Evolutionary","t":1587139231.515695,"i":85}
{"n":"Mixer","m":"ConcurrentEA","t":1587139231.515945,"i":88,"k":2,"c":"Concurrent"}
{"c":"Concurrent","k":1,"t":1587139231.51631,"i":89,"m":"ConcurrentEA","n":"Evolutionary","p":0,"d":{}}
{"k":0,"c":"Events","p":89,"d":{"population-size":512,"distinct-elements":512},"t":1587139231.826617,"m":"ConcurrentEA","n":"GenerationsStart"}
{"p":89,"d":{"id":8,"count":17,"best":54},"t":1587139236.269742,"n":"Events","m":"ConcurrentEA","k":0,"c":"Events"}
{"p":0,"d":{},"t":1587139236.289805,"i":90,"n":"Mixer","m":"ConcurrentEA","k":1,"c":"Concurrent"}
{"p":89,"d":{"generations":17,"individuals":9179},"t":1587139236.290415,"n":"Generations","m":"ConcurrentEA","k":0,"c":"Events"}
{"c":"Concurrent","k":2,"t":1587139236.290705,"i":89,"m":"ConcurrentEA","n":"Evolutionary"}
{"c":"Concurrent","k":2,"n":"Mixer","m":"ConcurrentEA","t":1587139236.291159,"i":90}
{"n":"Evolutionary","m":"ConcurrentEA","i":91,"t":1587139236.291395,"d":{},"p":0,"c":"Concurrent","k":1}
{"k":0,"c":"Events","p":91,"d":{"population-size":512,"distinct-elements":512},"t":1587139236.601838,"n":"GenerationsStart","m":"ConcurrentEA"}
{"c":"Events","k":0,"t":1587139237.743125,"m":"ConcurrentEA","n":"Events","p":87,"d":{"count":25,"best":56,"id":4}}
{"n":"Mixer","m":"ConcurrentEA","t":1587139237.762861,"i":92,"d":{},"p":0,"c":"Concurrent","k":1}
{"k":0,"c":"Events","p":87,"d":{"individuals":13254,"generations":25},"t":1587139237.76411,"m":"ConcurrentEA","n":"Generations"}
{"k":2,"c":"Concurrent","m":"ConcurrentEA","n":"Mixer","t":1587139237.764277,"i":92}
{"c":"Concurrent","k":2,"n":"Disturbance","m":"ConcurrentEA","i":87,"t":1587139237.764356}
{"t":1587139237.764756,"i":93,"m":"ConcurrentEA","n":"Disturbance","p":0,"d":{},"c":"Concurrent","k":1}
{"k":0,"c":"Events","p":93,"d":{"distinct-elements":512,"population-size":512},"t":1587139238.071458,"n":"GenerationsStart","m":"ConcurrentEA"}
{"p":91,"d":{"id":8,"count":17,"best":51},"t":1587139241.02924,"m":"ConcurrentEA","n":"Events","k":0,"c":"Events"}
{"n":"Mixer","m":"ConcurrentEA","t":1587139241.049088,"i":94,"d":{},"p":0,"c":"Concurrent","k":1}
{"n":"Generations","m":"ConcurrentEA","t":1587139241.053016,"d":{"individuals":9183,"generations":17},"p":91,"c":"Events","k":0}
{"c":"Concurrent","k":2,"n":"Evolutionary","m":"ConcurrentEA","t":1587139241.053327,"i":91}
{"n":"Mixer","m":"ConcurrentEA","t":1587139241.053381,"i":94,"k":2,"c":"Concurrent"}
{"c":"Concurrent","k":1,"i":95,"t":1587139241.053853,"n":"Evolutionary","m":"ConcurrentEA","p":0,"d":{}}
{"d":{"distinct-elements":512,"population-size":512},"p":95,"n":"GenerationsStart","m":"ConcurrentEA","t":1587139241.36745,"k":0,"c":"Events"}
{"k":0,"c":"Events","d":{"id":6,"count":25,"best":52},"p":93,"n":"Events","m":"ConcurrentEA","t":1587139244.63006}
{"d":{},"p":0,"n":"Mixer","m":"ConcurrentEA","i":96,"t":1587139244.653905,"k":1,"c":"Concurrent"}
{"i":96,"t":1587139244.655143,"n":"Mixer","m":"ConcurrentEA","c":"Concurrent","k":2}
{"k":0,"c":"Events","p":93,"d":{"generations":25,"individuals":13240},"t":1587139244.655192,"n":"Generations","m":"ConcurrentEA"}
{"k":2,"c":"Concurrent","n":"Disturbance","m":"ConcurrentEA","i":93,"t":1587139244.655479}
{"t":1587139244.655872,"i":97,"n":"Disturbance","m":"ConcurrentEA","p":0,"d":{},"c":"Concurrent","k":1}
{"c":"Events","k":0,"t":1587139244.965094,"m":"ConcurrentEA","n":"GenerationsStart","p":97,"d":{"distinct-elements":512,"population-size":512}}
{"k":0,"c":"Events","d":{"id":4,"count":17,"best":55},"p":95,"m":"ConcurrentEA","n":"Events","t":1587139245.861846}
{"d":{},"p":0,"n":"Mixer","m":"ConcurrentEA","t":1587139245.881737,"i":98,"k":1,"c":"Concurrent"}
{"t":1587139245.882637,"n":"Generations","m":"ConcurrentEA","p":95,"d":{"generations":17,"individuals":9178},"c":"Events","k":0}
{"i":95,"t":1587139245.882934,"n":"Evolutionary","m":"ConcurrentEA","k":2,"c":"Concurrent"}
{"i":98,"t":1587139245.882988,"n":"Mixer","m":"ConcurrentEA","k":2,"c":"Concurrent"}
{"p":0,"d":{},"i":99,"t":1587139245.883475,"n":"Evolutionary","m":"ConcurrentEA","k":1,"c":"Concurrent"}
{"c":"Events","k":0,"t":1587139246.193873,"m":"ConcurrentEA","n":"GenerationsStart","p":99,"d":{"population-size":512,"distinct-elements":512}}
{"t":1587139250.747874,"m":"ConcurrentEA","n":"Events","p":99,"d":{"best":53,"count":17,"id":4},"c":"Events","k":0}
{"n":"Mixer","m":"ConcurrentEA","t":1587139250.770883,"i":100,"d":{},"p":0,"c":"Concurrent","k":1}
{"d":{"individuals":9174,"generations":17},"p":99,"m":"ConcurrentEA","n":"Generations","t":1587139250.771527,"k":0,"c":"Events"}
{"c":"Concurrent","k":2,"n":"Evolutionary","m":"ConcurrentEA","i":99,"t":1587139250.771838}
{"m":"ConcurrentEA","n":"Mixer","t":1587139250.772102,"i":100,"c":"Concurrent","k":2}
{"c":"Concurrent","k":1,"m":"ConcurrentEA","n":"Evolutionary","t":1587139250.772444,"i":101,"d":{},"p":0}
{"c":"Events","k":0,"t":1587139251.07841,"m":"ConcurrentEA","n":"GenerationsStart","p":101,"d":{"distinct-elements":512,"population-size":512}}
{"t":1587139251.545202,"m":"ConcurrentEA","n":"Events","p":97,"d":{"best":53,"count":25,"id":8},"c":"Events","k":0}
{"t":1587139251.5697,"i":102,"n":"Mixer","m":"ConcurrentEA","p":0,"d":{},"c":"Concurrent","k":1}
{"p":97,"d":{"individuals":13262,"generations":25},"t":1587139251.57031,"m":"ConcurrentEA","n":"Generations","k":0,"c":"Events"}
{"i":97,"t":1587139251.5706,"n":"Disturbance","m":"ConcurrentEA","k":2,"c":"Concurrent"}
{"t":1587139251.570922,"i":102,"n":"Mixer","m":"ConcurrentEA","k":2,"c":"Concurrent"}
{"n":"Disturbance","m":"ConcurrentEA","i":103,"t":1587139251.571197,"d":{},"p":0,"c":"Concurrent","k":1}
{"d":{"distinct-elements":511,"population-size":512},"p":103,"m":"ConcurrentEA","n":"GenerationsStart","t":1587139251.886873,"k":0,"c":"Events"}
{"k":0,"c":"Events","d":{"id":6,"count":17,"best":53},"p":101,"m":"ConcurrentEA","n":"Events","t":1587139255.507165}
{"t":1587139255.530675,"i":104,"m":"ConcurrentEA","n":"Mixer","p":0,"d":{},"c":"Concurrent","k":1}
{"p":101,"d":{"generations":17,"individuals":9171},"t":1587139255.531557,"m":"ConcurrentEA","n":"Generations","k":0,"c":"Events"}
{"m":"ConcurrentEA","n":"Evolutionary","t":1587139255.531807,"i":101,"c":"Concurrent","k":2}
{"c":"Concurrent","k":2,"i":104,"t":1587139255.531874,"n":"Mixer","m":"ConcurrentEA"}
{"d":{},"p":0,"m":"ConcurrentEA","n":"Evolutionary","t":1587139255.532298,"i":105,"k":1,"c":"Concurrent"}
{"p":105,"d":{"distinct-elements":512,"population-size":512},"t":1587139255.843958,"m":"ConcurrentEA","n":"GenerationsStart","k":0,"c":"Events"}
{"c":"Events","k":0,"n":"Events","m":"ConcurrentEA","t":1587139258.421861,"d":{"best":55,"count":25,"id":8},"p":103}
{"c":"Concurrent","k":1,"n":"Mixer","m":"ConcurrentEA","i":106,"t":1587139258.446594,"d":{},"p":0}
{"p":103,"d":{"individuals":13256,"generations":25},"t":1587139258.447447,"m":"ConcurrentEA","n":"Generations","k":0,"c":"Events"}
{"k":2,"c":"Concurrent","m":"ConcurrentEA","n":"Disturbance","i":103,"t":1587139258.44773}
{"c":"Concurrent","k":2,"m":"ConcurrentEA","n":"Mixer","t":1587139258.447853,"i":106}
{"c":"Concurrent","k":1,"n":"Disturbance","m":"ConcurrentEA","t":1587139258.448258,"i":107,"d":{},"p":0}
{"k":0,"c":"Events","p":107,"d":{"distinct-elements":511,"population-size":512},"t":1587139258.814649,"m":"ConcurrentEA","n":"GenerationsStart"}
{"n":"Events","m":"ConcurrentEA","t":1587139260.32562,"d":{"count":17,"best":53,"id":4},"p":105,"c":"Events","k":0}
{"k":1,"c":"Concurrent","p":0,"d":{},"t":1587139260.350365,"i":108,"m":"ConcurrentEA","n":"Mixer"}
{"d":{"generations":17,"individuals":9178},"p":105,"n":"Generations","m":"ConcurrentEA","t":1587139260.350744,"k":0,"c":"Events"}
{"m":"ConcurrentEA","n":"Evolutionary","i":105,"t":1587139260.351045,"c":"Concurrent","k":2}
{"t":1587139260.351891,"i":108,"n":"Mixer","m":"ConcurrentEA","c":"Concurrent","k":2}
{"k":1,"c":"Concurrent","p":0,"d":{},"i":109,"t":1587139260.351964,"m":"ConcurrentEA","n":"Evolutionary"}
{"c":"Events","k":0,"t":1587139260.668255,"m":"ConcurrentEA","n":"GenerationsStart","p":109,"d":{"distinct-elements":512,"population-size":512}}
{"d":{"count":17,"best":53,"id":4},"p":109,"n":"Events","m":"ConcurrentEA","t":1587139265.135073,"k":0,"c":"Events"}
{"p":0,"d":{},"i":110,"t":1587139265.154869,"n":"Mixer","m":"ConcurrentEA","k":1,"c":"Concurrent"}
{"p":109,"d":{"individuals":9173,"generations":17},"t":1587139265.155716,"n":"Generations","m":"ConcurrentEA","k":0,"c":"Events"}
{"t":1587139265.156023,"i":109,"m":"ConcurrentEA","n":"Evolutionary","c":"Concurrent","k":2}
{"i":110,"t":1587139265.156067,"m":"ConcurrentEA","n":"Mixer","k":2,"c":"Concurrent"}
{"k":1,"c":"Concurrent","p":0,"d":{},"t":1587139265.156524,"i":111,"n":"Evolutionary","m":"ConcurrentEA"}
{"d":{"best":55,"count":25,"id":6},"p":107,"m":"ConcurrentEA","n":"Events","t":1587139265.321096,"k":0,"c":"Events"}
{"n":"Mixer","m":"ConcurrentEA","i":112,"t":1587139265.342182,"d":{},"p":0,"c":"Concurrent","k":1}
{"m":"ConcurrentEA","n":"Mixer","i":112,"t":1587139265.343331,"k":2,"c":"Concurrent"}
{"k":0,"c":"Events","d":{"generations":25,"individuals":13262},"p":107,"m":"ConcurrentEA","n":"Generations","t":1587139265.343505}
{"c":"Concurrent","k":2,"n":"Disturbance","m":"ConcurrentEA","i":107,"t":1587139265.343727}
{"c":"Concurrent","k":1,"t":1587139265.344076,"i":113,"m":"ConcurrentEA","n":"Disturbance","p":0,"d":{}}
{"k":0,"c":"Events","d":{"population-size":512,"distinct-elements":512},"p":111,"m":"ConcurrentEA","n":"GenerationsStart","t":1587139265.472758}
{"c":"Events","k":0,"n":"GenerationsStart","m":"ConcurrentEA","t":1587139265.648492,"d":{"population-size":512,"distinct-elements":512},"p":113}
{"m":"ConcurrentEA","n":"Events","t":1587139269.895896,"d":{"id":4,"count":17,"best":49},"p":111,"c":"Events","k":0}
{"i":114,"t":1587139269.91589,"n":"Mixer","m":"ConcurrentEA","p":0,"d":{},"c":"Concurrent","k":1}
{"d":{"generations":17,"individuals":9180},"p":111,"m":"ConcurrentEA","n":"Generations","t":1587139269.916585,"k":0,"c":"Events"}
{"m":"ConcurrentEA","n":"Evolutionary","t":1587139269.916865,"i":111,"k":2,"c":"Concurrent"}
{"c":"Concurrent","k":2,"n":"Mixer","m":"ConcurrentEA","t":1587139269.91713,"i":114}
{"n":"Evolutionary","m":"ConcurrentEA","i":115,"t":1587139269.91745,"d":{},"p":0,"c":"Concurrent","k":1}
{"p":115,"d":{"population-size":512,"distinct-elements":512},"t":1587139270.235778,"n":"GenerationsStart","m":"ConcurrentEA","k":0,"c":"Events"}
{"c":"Events","k":0,"t":1587139272.178475,"n":"Events","m":"ConcurrentEA","p":113,"d":{"count":25,"best":56,"id":8}}
{"c":"Concurrent","k":1,"t":1587139272.202341,"i":116,"n":"Mixer","m":"ConcurrentEA","p":0,"d":{}}
{"m":"ConcurrentEA","n":"Mixer","i":116,"t":1587139272.203537,"k":2,"c":"Concurrent"}
{"m":"ConcurrentEA","n":"Generations","t":1587139272.203636,"d":{"individuals":13252,"generations":25},"p":113,"c":"Events","k":0}
{"n":"Disturbance","m":"ConcurrentEA","t":1587139272.203851,"i":113,"c":"Concurrent","k":2}
{"c":"Concurrent","k":1,"m":"ConcurrentEA","n":"Disturbance","i":117,"t":1587139272.204225,"d":{},"p":0}
{"c":"Events","k":0,"t":1587139272.511533,"m":"ConcurrentEA","n":"GenerationsStart","p":117,"d":{"population-size":512,"distinct-elements":512}}
{"m":"ConcurrentEA","n":"Events","t":1587139274.673853,"d":{"id":4,"count":17,"best":49},"p":115,"c":"Events","k":0}
{"c":"Concurrent","k":1,"t":1587139274.696602,"i":118,"n":"Mixer","m":"ConcurrentEA","p":0,"d":{}}
{"k":0,"c":"Events","p":115,"d":{"generations":17,"individuals":9187},"t":1587139274.697759,"n":"Generations","m":"ConcurrentEA"}
{"m":"ConcurrentEA","n":"Mixer","i":118,"t":1587139274.697913,"c":"Concurrent","k":2}
{"i":115,"t":1587139274.698075,"m":"ConcurrentEA","n":"Evolutionary","c":"Concurrent","k":2}
{"p":0,"d":{},"i":119,"t":1587139274.69847,"m":"ConcurrentEA","n":"Evolutionary","k":1,"c":"Concurrent"}
{"k":0,"c":"Events","p":119,"d":{"distinct-elements":512,"population-size":512},"t":1587139275.004453,"m":"ConcurrentEA","n":"GenerationsStart"}
{"k":0,"c":"Events","p":117,"d":{"count":25,"best":56,"id":6},"t":1587139279.052688,"m":"ConcurrentEA","n":"Events"}
{"d":{},"p":0,"n":"Mixer","m":"ConcurrentEA","i":120,"t":1587139279.073107,"k":1,"c":"Concurrent"}
{"p":117,"d":{"generations":25,"individuals":13266},"t":1587139279.074171,"m":"ConcurrentEA","n":"Generations","k":0,"c":"Events"}
{"t":1587139279.074328,"i":120,"m":"ConcurrentEA","n":"Mixer","c":"Concurrent","k":2}
{"k":2,"c":"Concurrent","i":117,"t":1587139279.074477,"n":"Disturbance","m":"ConcurrentEA"}
{"d":{},"p":0,"m":"ConcurrentEA","n":"Disturbance","t":1587139279.074856,"i":121,"k":1,"c":"Concurrent"}
{"c":"Events","k":0,"m":"ConcurrentEA","n":"GenerationsStart","t":1587139279.384277,"d":{"population-size":512,"distinct-elements":512},"p":121}
{"p":119,"d":{"id":8,"best":53,"count":17},"t":1587139279.438296,"m":"ConcurrentEA","n":"Events","k":0,"c":"Events"}
{"i":122,"t":1587139279.458374,"m":"ConcurrentEA","n":"Mixer","p":0,"d":{},"c":"Concurrent","k":1}
{"p":119,"d":{"individuals":9189,"generations":17},"t":1587139279.459106,"n":"Generations","m":"ConcurrentEA","k":0,"c":"Events"}
{"n":"Evolutionary","m":"ConcurrentEA","t":1587139279.459407,"i":119,"k":2,"c":"Concurrent"}
{"m":"ConcurrentEA","n":"Mixer","i":122,"t":1587139279.459577,"k":2,"c":"Concurrent"}
{"c":"Concurrent","k":1,"t":1587139279.459991,"i":123,"n":"Evolutionary","m":"ConcurrentEA","p":0,"d":{}}
{"t":1587139279.76988,"n":"GenerationsStart","m":"ConcurrentEA","p":123,"d":{"distinct-elements":512,"population-size":512},"c":"Events","k":0}
{"n":"Events","m":"ConcurrentEA","t":1587139284.20552,"d":{"id":8,"count":17,"best":53},"p":123,"c":"Events","k":0}
{"d":{},"p":0,"n":"Mixer","m":"ConcurrentEA","i":124,"t":1587139284.225231,"k":1,"c":"Concurrent"}
{"p":123,"d":{"generations":17,"individuals":9190},"t":1587139284.225924,"n":"Generations","m":"ConcurrentEA","k":0,"c":"Events"}
{"n":"Evolutionary","m":"ConcurrentEA","t":1587139284.226192,"i":123,"k":2,"c":"Concurrent"}
{"c":"Concurrent","k":2,"n":"Mixer","m":"ConcurrentEA","i":124,"t":1587139284.226422}
{"p":0,"d":{},"t":1587139284.22675,"i":125,"m":"ConcurrentEA","n":"Evolutionary","k":1,"c":"Concurrent"}
{"k":0,"c":"Events","p":125,"d":{"population-size":512,"distinct-elements":512},"t":1587139284.587287,"n":"GenerationsStart","m":"ConcurrentEA"}
{"c":"Events","k":0,"t":1587139285.940447,"n":"Events","m":"ConcurrentEA","p":121,"d":{"count":25,"best":53,"id":4}}
{"i":126,"t":1587139285.961276,"m":"ConcurrentEA","n":"Mixer","p":0,"d":{},"c":"Concurrent","k":1}
{"c":"Events","k":0,"n":"Generations","m":"ConcurrentEA","t":1587139285.962343,"d":{"individuals":13262,"generations":25},"p":121}
{"m":"ConcurrentEA","n":"Disturbance","t":1587139285.962615,"i":121,"k":2,"c":"Concurrent"}
{"t":1587139285.962756,"i":126,"m":"ConcurrentEA","n":"Mixer","k":2,"c":"Concurrent"}
{"t":1587139285.963206,"i":127,"m":"ConcurrentEA","n":"Disturbance","p":0,"d":{},"c":"Concurrent","k":1}
{"c":"Events","k":0,"t":1587139286.280055,"n":"GenerationsStart","m":"ConcurrentEA","p":127,"d":{"distinct-elements":512,"population-size":512}}
{"t":1587139288.988685,"n":"Events","m":"ConcurrentEA","p":125,"d":{"id":6,"count":17,"best":49},"c":"Events","k":0}
{"d":{},"p":0,"m":"ConcurrentEA","n":"Mixer","i":128,"t":1587139289.008614,"k":1,"c":"Concurrent"}
{"n":"Generations","m":"ConcurrentEA","t":1587139289.00949,"d":{"individuals":9180,"generations":17},"p":125,"c":"Events","k":0}
{"k":2,"c":"Concurrent","i":125,"t":1587139289.00969,"n":"Evolutionary","m":"ConcurrentEA"}
{"k":2,"c":"Concurrent","n":"Mixer","m":"ConcurrentEA","i":128,"t":1587139289.009754}
{"t":1587139289.010133,"i":129,"n":"Evolutionary","m":"ConcurrentEA","p":0,"d":{},"c":"Concurrent","k":1}
{"t":1587139289.368024,"n":"GenerationsStart","m":"ConcurrentEA","p":129,"d":{"distinct-elements":512,"population-size":512},"c":"Events","k":0}
{"m":"ConcurrentEA","n":"Events","t":1587139292.81755,"d":{"id":4,"best":51,"count":25},"p":127,"c":"Events","k":0}
{"d":{},"p":0,"n":"Mixer","m":"ConcurrentEA","i":130,"t":1587139292.841847,"k":1,"c":"Concurrent"}
{"p":127,"d":{"generations":25,"individuals":13263},"t":1587139292.842916,"m":"ConcurrentEA","n":"Generations","k":0,"c":"Events"}
{"m":"ConcurrentEA","n":"Mixer","i":130,"t":1587139292.84303,"k":2,"c":"Concurrent"}
{"c":"Concurrent","k":2,"t":1587139292.843202,"i":127,"n":"Disturbance","m":"ConcurrentEA"}
{"p":0,"d":{},"i":131,"t":1587139292.843606,"m":"ConcurrentEA","n":"Disturbance","k":1,"c":"Concurrent"}
{"k":0,"c":"Events","d":{"population-size":512,"distinct-elements":511},"p":131,"n":"GenerationsStart","m":"ConcurrentEA","t":1587139293.157165}
{"p":129,"d":{"count":17,"best":52,"id":8},"t":1587139293.753273,"n":"Events","m":"ConcurrentEA","k":0,"c":"Events"}
{"k":1,"c":"Concurrent","p":0,"d":{},"t":1587139293.772874,"i":132,"n":"Mixer","m":"ConcurrentEA"}
{"n":"Generations","m":"ConcurrentEA","t":1587139293.777018,"d":{"generations":17,"individuals":9186},"p":129,"c":"Events","k":0}
{"n":"Mixer","m":"ConcurrentEA","t":1587139293.777157,"i":132,"c":"Concurrent","k":2}
{"k":2,"c":"Concurrent","m":"ConcurrentEA","n":"Evolutionary","t":1587139293.777325,"i":129}
{"c":"Concurrent","k":1,"m":"ConcurrentEA","n":"Evolutionary","i":133,"t":1587139293.777788,"d":{},"p":0}
{"p":133,"d":{"population-size":512,"distinct-elements":512},"t":1587139294.138406,"m":"ConcurrentEA","n":"GenerationsStart","k":0,"c":"Events"}
{"t":1587139298.654174,"m":"ConcurrentEA","n":"Events","p":133,"d":{"id":4,"count":17,"best":55},"c":"Events","k":0}
{"n":"Mixer","m":"ConcurrentEA","i":134,"t":1587139298.673822,"d":{},"p":0,"c":"Concurrent","k":1}
{"t":1587139298.674679,"m":"ConcurrentEA","n":"Generations","p":133,"d":{"individuals":9171,"generations":17},"c":"Events","k":0}
{"k":2,"c":"Concurrent","t":1587139298.674888,"i":133,"m":"ConcurrentEA","n":"Evolutionary"}
{"k":2,"c":"Concurrent","m":"ConcurrentEA","n":"Mixer","i":134,"t":1587139298.674974}
{"k":1,"c":"Concurrent","d":{},"p":0,"n":"Evolutionary","m":"ConcurrentEA","i":135,"t":1587139298.675359}
{"c":"Events","k":0,"m":"ConcurrentEA","n":"GenerationsStart","t":1587139298.995108,"d":{"distinct-elements":512,"population-size":512},"p":135}
{"p":131,"d":{"count":25,"best":56,"id":6},"t":1587139299.682111,"n":"Events","m":"ConcurrentEA","k":0,"c":"Events"}
{"d":{},"p":0,"n":"Mixer","m":"ConcurrentEA","i":136,"t":1587139299.702275,"k":1,"c":"Concurrent"}
{"n":"Mixer","m":"ConcurrentEA","t":1587139299.703445,"i":136,"k":2,"c":"Concurrent"}
{"k":0,"c":"Events","d":{"individuals":13250,"generations":25},"p":131,"n":"Generations","m":"ConcurrentEA","t":1587139299.703571}
{"c":"Concurrent","k":2,"i":131,"t":1587139299.703841,"n":"Disturbance","m":"ConcurrentEA"}
{"k":1,"c":"Concurrent","p":0,"d":{},"i":137,"t":1587139299.704242,"m":"ConcurrentEA","n":"Disturbance"}
{"c":"Events","k":0,"t":1587139300.013023,"n":"GenerationsStart","m":"ConcurrentEA","p":137,"d":{"population-size":512,"distinct-elements":512}}
{"p":0,"d":{},"t":1587139302.696629,"n":"SolutionFound","m":"ConcurrentEA","k":0,"c":"Events"}
{"d":{"evaluations":709645},"p":135,"n":"SolutionFound","m":"ConcurrentEA","t":1587139302.697146,"k":0,"c":"Events"}
{"d":{"distinct-elements":7646,"id":4,"population-size":512,"best":60,"count":14},"p":135,"n":"Weird","m":"ConcurrentEA","t":1587139302.710108,"k":0,"c":"Events"}
{"p":0,"d":{},"i":138,"t":1587139302.729949,"m":"ConcurrentEA","n":"Mixer","k":1,"c":"Concurrent"}
{"k":0,"c":"Events","d":{"individuals":7646,"generations":14},"p":135,"n":"Generations","m":"ConcurrentEA","t":1587139302.730558}
{"c":"Concurrent","k":2,"m":"ConcurrentEA","n":"Evolutionary","i":135,"t":1587139302.730841}
{"k":2,"c":"Concurrent","n":"Mixer","m":"ConcurrentEA","t":1587139302.731552,"i":138}
{"k":0,"c":"Events","d":{"count":25,"best":52,"id":8},"p":137,"m":"ConcurrentEA","n":"Events","t":1587139306.38156}
{"c":"Events","k":0,"n":"Generations","m":"ConcurrentEA","t":1587139306.399235,"d":{"individuals":13261,"generations":25},"p":137}
{"c":"Concurrent","k":2,"i":137,"t":1587139306.399491,"m":"ConcurrentEA","n":"Disturbance"}
